pycmdtools/__init__.py
pycmdtools/configs.py
pycmdtools/main.py
pycmdtools/python.py
pycmdtools/static.py
pycmdtools/utils.py
pycmdtools-0.0.85.dist-info/LICENSE
pycmdtools-0.0.85.dist-info/METADATA
pycmdtools-0.0.85.dist-info/WHEEL
pycmdtools-0.0.85.dist-info/entry_points.txt
pycmdtools-0.0.85.dist-info/top_level.txt
pycmdtools-0.0.85.dist-info/RECORD
