Metadata-Version: 2.1
Name: pycmdtools
Version: 0.0.85
Summary: pycmdtools is set of useful command line tools written in python
Home-page: https://veltzer.github.io/pycmdtools
Download-URL: https://github.com/veltzer/pycmdtools
Author: Mark Veltzer
Author-email: mark.veltzer@gmail.com
Maintainer: Mark Veltzer
Maintainer-email: mark.veltzer@gmail.com
License: MIT
Keywords: utils,command-line,python,shell,utilities
Platform: python3
Classifier: Development Status :: 4 - Beta
Classifier: Environment :: Console
Classifier: Operating System :: OS Independent
Classifier: Programming Language :: Python
Classifier: Programming Language :: Python :: 3
Classifier: Programming Language :: Python :: 3 :: Only
Classifier: Programming Language :: Python :: 3.11
Classifier: Topic :: Utilities
Classifier: License :: OSI Approved :: MIT License
License-File: LICENSE
Requires-Dist: pylogconf
Requires-Dist: pytconf
Requires-Dist: requests
Requires-Dist: types-requests
Requires-Dist: tqdm
Requires-Dist: numpy
Requires-Dist: pandas
Requires-Dist: unidecode
Requires-Dist: pyyaml
Requires-Dist: jsonschema
Requires-Dist: pytidylib
Requires-Dist: beautifulsoup4
Requires-Dist: lxml
Requires-Dist: html5lib
